{
  "airtel_stores": [
    {
      "city": "Delhi",
      "store_name": "Airtel Connaught Place",
      "address": "C-7, Connaught Place, New Delhi - 110001",
      "phone": "011-23456789"
    },
    {
      "city": "Delhi",
      "store_name": "Airtel Lajpat Nagar",
      "address": "B-12, Lajpat Nagar II, New Delhi - 110024",
      "phone": "011-22334455"
    },
    {
      "city": "Delhi",
      "store_name": "Airtel Saket",
      "address": "F-26, Select City Walk, Saket, New Delhi - 110017",
      "phone": "011-22778899"
    },
    {
      "city": "Mumbai",
      "store_name": "Airtel Andheri West",
      "address": "Shop No. 2, Andheri Link Road, Mumbai - 400053",
      "phone": "022-22334411"
    },
    {
      "city": "Mumbai",
      "store_name": "Airtel Dadar",
      "address": "G-10, Dadar Plaza, Mumbai - 400014",
      "phone": "022-22334422"
    },
    {
      "city": "Mumbai",
      "store_name": "Airtel Borivali",
      "address": "104, Western Heights, Borivali West, Mumbai - 400092",
      "phone": "022-22334433"
    },
    {
      "city": "Bangalore",
      "store_name": "Airtel MG Road",
      "address": "24, MG Road, Bangalore - 560001",
      "phone": "080-22112211"
    },
    {
      "city": "Bangalore",
      "store_name": "Airtel Indiranagar",
      "address": "12th Main, 100 Feet Rd, Indiranagar, Bangalore - 560038",
      "phone": "080-22112222"
    },
    {
      "city": "Bangalore",
      "store_name": "Airtel Whitefield",
      "address": "Forum Mall, Whitefield, Bangalore - 560066",
      "phone": "080-22112233"
    },
    {
      "city": "Chennai",
      "store_name": "Airtel T Nagar",
      "address": "56, Usman Road, T Nagar, Chennai - 600017",
      "phone": "044-33445511"
    },
    {
      "city": "Chennai",
      "store_name": "Airtel Adyar",
      "address": "2nd Ave, Adyar, Chennai - 600020",
      "phone": "044-33445522"
    },
    {
      "city": "Chennai",
      "store_name": "Airtel Velachery",
      "address": "Phoenix Marketcity, Velachery, Chennai - 600042",
      "phone": "044-33445533"
    },
    {
      "city": "Hyderabad",
      "store_name": "Airtel Banjara Hills",
      "address": "Rd No. 12, Banjara Hills, Hyderabad - 500034",
      "phone": "040-33442211"
    },
    {
      "city": "Hyderabad",
      "store_name": "Airtel Hitech City",
      "address": "Inorbit Mall, Hitech City, Hyderabad - 500081",
      "phone": "040-33442222"
    },
    {
      "city": "Hyderabad",
      "store_name": "Airtel Kukatpally",
      "address": "Main Rd, Kukatpally, Hyderabad - 500072",
      "phone": "040-33442233"
    },
    {
      "city": "Kolkata",
      "store_name": "Airtel Park Street",
      "address": "20B, Park Street, Kolkata - 700016",
      "phone": "033-44556611"
    },
    {
      "city": "Kolkata",
      "store_name": "Airtel Salt Lake",
      "address": "Sector V, Salt Lake City, Kolkata - 700091",
      "phone": "033-44556622"
    },
    {
      "city": "Kolkata",
      "store_name": "Airtel Gariahat",
      "address": "Gariahat Road, Ballygunge, Kolkata - 700019",
      "phone": "033-44556633"
    },
    {
      "city": "Pune",
      "store_name": "Airtel Deccan",
      "address": "JM Road, Deccan, Pune - 411004",
      "phone": "020-22331111"
    },
    {
      "city": "Pune",
      "store_name": "Airtel Viman Nagar",
      "address": "Phoenix Marketcity, Viman Nagar, Pune - 411014",
      "phone": "020-22331122"
    },
    {
      "city": "Pune",
      "store_name": "Airtel Baner",
      "address": "Baner Road, Pune - 411045",
      "phone": "020-22331133"
    },
    {
      "city": "Ahmedabad",
      "store_name": "Airtel SG Highway",
      "address": "SG Highway, Ahmedabad - 380015",
      "phone": "079-22334411"
    },
    {
      "city": "Ahmedabad",
      "store_name": "Airtel Maninagar",
      "address": "Maninagar East, Ahmedabad - 380008",
      "phone": "079-22334422"
    },
    {
      "city": "Ahmedabad",
      "store_name": "Airtel Navrangpura",
      "address": "Near Vijay Cross Rd, Navrangpura, Ahmedabad - 380009",
      "phone": "079-22334433"
    },
    {
      "city": "Jaipur",
      "store_name": "Airtel MI Road",
      "address": "Mirza Ismail Road, Jaipur - 302001",
      "phone": "0141-66778811"
    },
    {
      "city": "Jaipur",
      "store_name": "Airtel Malviya Nagar",
      "address": "GT Road, Malviya Nagar, Jaipur - 302017",
      "phone": "0141-66778822"
    },
    {
      "city": "Lucknow",
      "store_name": "Airtel Hazratganj",
      "address": "MG Road, Hazratganj, Lucknow - 226001",
      "phone": "0522-33445566"
    },
    {
      "city": "Lucknow",
      "store_name": "Airtel Gomti Nagar",
      "address": "Vibhuti Khand, Gomti Nagar, Lucknow - 226010",
      "phone": "0522-33445577"
    },
    {
      "city": "Bhopal",
      "store_name": "Airtel MP Nagar",
      "address": "Zone II, MP Nagar, Bhopal - 462011",
      "phone": "0755-12345678"
    },
    {
      "city": "Indore",
      "store_name": "Airtel Vijay Nagar",
      "address": "AB Road, Vijay Nagar, Indore - 452010",
      "phone": "0731-87654321"
    }
  ]
}
